nummu/__init__.py
nummu/core.py
nummu/draw.py
nummu/errors.py
nummu-0.1.9.dist-info/LICENSE
nummu-0.1.9.dist-info/WHEEL
nummu-0.1.9.dist-info/METADATA
nummu-0.1.9.dist-info/RECORD
